LDAQ/__init__.py
LDAQ/__main__.py
LDAQ/acquisition_base.py
LDAQ/control_base.py
LDAQ/core.py
LDAQ/generation_base.py
LDAQ/logo.png
LDAQ/utils.py
LDAQ/basler/__init__.py
LDAQ/basler/acquisition.py
LDAQ/bluetooth/__init__.py
LDAQ/bluetooth/acquisition.py
LDAQ/dewesoft/__init__.py
LDAQ/dewesoft/acquisition.py
LDAQ/digilent/__init__.py
LDAQ/digilent/acquisition.py
LDAQ/digilent/dwfconstants.py
LDAQ/flir/__init__.py
LDAQ/flir/acquisition.py
LDAQ/national_instruments/__init__.py
LDAQ/national_instruments/acquisition.py
LDAQ/national_instruments/daqtask.py
LDAQ/national_instruments/generation.py
LDAQ/national_instruments/ni_task.py
LDAQ/serial_communication/__init__.py
LDAQ/serial_communication/acquisition.py
LDAQ/simulator/__init__.py
LDAQ/simulator/acquisition.py
LDAQ/visualization/__init__.py
LDAQ/visualization/flask_app.py
LDAQ/visualization/visualization.py
LDAQ/visualization/visualization_helpers.py
LDAQ/visualization/visualization_js.py
LDAQ/visualization/templates/index.html
ldaq-1.2.0.dist-info/METADATA
ldaq-1.2.0.dist-info/WHEEL
ldaq-1.2.0.dist-info/RECORD
