Metadata-Version: 2.4
Name: LDAQ
Version: 1.2.0
Summary: Data acquisition and generation with live visualization.
Project-URL: homepage, https://github.com/ladisk/LDAQ
Project-URL: documentation, https://ldaq.readthedocs.io/en/latest/
Project-URL: source, https://github.com/ladisk/LDAQ
Author-email: "Tilen Košir, Klemen Zaletelj, Janko Slavič" <janko.slavic@fs.uni-lj.si>
Maintainer-email: "Tilen Košir, Klemen Zaletelj" <klemen.zaletelj@fs.uni-lj.si>
License-Expression: MIT
Keywords: data acquisition,data generation,live visualization
Classifier: Development Status :: 5 - Production/Stable
Classifier: Intended Audience :: Developers
Classifier: License :: OSI Approved :: MIT License
Classifier: Programming Language :: Python :: 3.10
Classifier: Topic :: Scientific/Engineering
Requires-Python: >=3.10
Requires-Dist: beautifultable>=1.1.0
Requires-Dist: dill
Requires-Dist: keyboard
Requires-Dist: matplotlib
Requires-Dist: nidaqmx>=0.8.0
Requires-Dist: numpy>=1.11.0
Requires-Dist: openpyxl
Requires-Dist: pandas>=2.0.0
Requires-Dist: pydaqmx>=1.3
Requires-Dist: pyqtgraph
Requires-Dist: pyserial
Requires-Dist: pytrigger
Requires-Dist: scipy>=1.2.0
Requires-Dist: sphinx-copybutton
Requires-Dist: tqdm
Requires-Dist: urllib3<2.0
Provides-Extra: dev
Requires-Dist: jupyter; extra == 'dev'
Requires-Dist: nbsphinx; extra == 'dev'
Requires-Dist: nbsphinx-link; extra == 'dev'
Requires-Dist: pytest; extra == 'dev'
Requires-Dist: sphinx; extra == 'dev'
Requires-Dist: sphinx-book-theme; extra == 'dev'
Requires-Dist: sphinx-rtd-theme; extra == 'dev'
Requires-Dist: tomli; extra == 'dev'
Requires-Dist: tomli-w; extra == 'dev'
Requires-Dist: twine; extra == 'dev'
Requires-Dist: wheel; extra == 'dev'
Provides-Extra: qt
Requires-Dist: pyqt6; extra == 'qt'
